README.rst
setup.cfg
setup.py
android_gradle_source_mover/__init__.py
android_gradle_source_mover/start.py
android_gradle_source_mover/version.py
android_gradle_source_mover.egg-info/PKG-INFO
android_gradle_source_mover.egg-info/SOURCES.txt
android_gradle_source_mover.egg-info/dependency_links.txt
android_gradle_source_mover.egg-info/top_level.txt
android_gradle_source_mover.egg-info/zip-safe