Metadata-Version: 1.1
Name: android-gradle-source-mover
Version: 0.1.7
Summary: A Android sources mover for gradle build.
Home-page: hhttps://github.com/mumaoxi/android_gradle_source_mover
Author: mumaoxi
Author-email: 15201280641@qq.com
License: MIT
Keywords: test python package
Platform: UNKNOWN
Classifier: License :: OSI Approved :: MIT License
Classifier: Programming Language :: Python
Classifier: Intended Audience :: Developers
Classifier: Operating System :: OS Independent
